nyx_space-2.0.0a2.dist-info/METADATA
nyx_space-2.0.0a2.dist-info/WHEEL
nyx_space-2.0.0a2.dist-info/license_files/LICENSE
nyx_space/__init__.py
nyx_space/utils/doris.py
nyx_space/utils/__init__.py
nyx_space/plots/__init__.py
nyx_space/plots/traj.py
nyx_space/plots/utils.py
nyx_space/plots/od.py
nyx_space/plots/gauss_markov.py
nyx_space/_nyx_space.cpython-310-x86_64-linux-gnu.so
nyx_space-2.0.0a2.dist-info/RECORD
