Metadata-Version: 2.1
Name: nyx_space
Version: 2.0.0a2
Classifier: Development Status :: 4 - Beta
Classifier: Topic :: Scientific/Engineering
Classifier: Topic :: Scientific/Engineering :: Physics
Classifier: Intended Audience :: Science/Research
Classifier: License :: OSI Approved :: GNU Affero General Public License v3 or later (AGPLv3+)
Requires-Dist: pandas~=2.0.0
Requires-Dist: plotly~=5.13.0
Requires-Dist: pytest~=7.2.0
Requires-Dist: pyarrow~=11.0.0
Requires-Dist: scipy~=1.10.1
Requires-Dist: python-slugify~=8.0.1
License-File: LICENSE
Summary: A high-fidelity space mission toolkit, with orbit propagation, estimation and some systems engineering
Keywords: space,mission,design,orbit,estimation
Home-Page: https://nyxspace.com
Author: Christopher Rabotin <christopher.rabotin@gmail.com>
Author-email: Christopher Rabotin <christopher.rabotin@gmail.com>
License: AGPL-3.0-or-later
Requires-Python: >=3.7
Project-URL: Source Code, https://gitlab.com/nyx-space/nyx
